skycalc_cli/__init__.py
skycalc_cli/skycalc.py
skycalc_cli/skycalc_cli.py
skycalc_cli-1.4.dist-info/DESCRIPTION.rst
skycalc_cli-1.4.dist-info/METADATA
skycalc_cli-1.4.dist-info/RECORD
skycalc_cli-1.4.dist-info/WHEEL
skycalc_cli-1.4.dist-info/entry_points.txt
skycalc_cli-1.4.dist-info/metadata.json
skycalc_cli-1.4.dist-info/top_level.txt
